<?xml version="1.0" ?>
<annotation>
   <folder/>
   <filename>PMC2964642_table_0.jpg</filename>
   <path>PMC2964642_table_0.jpg</path>
   <source>
      <database>PubTables1M-Structure</database>
   </source>
   <size>
      <width>357</width>
      <height>153</height>
      <depth>3</depth>
   </size>
   <segmented>0</segmented>
   <object>
      <name>table</name>
      <pose>Frontal</pose>
      <truncated>0</truncated>
      <difficult>0</difficult>
      <occluded>0</occluded>
      <bndbox>
         <xmin>36.4284</xmin>
         <ymin>36.9701</ymin>
         <xmax>318.6033</xmax>
         <ymax>113.9397</ymax>
      </bndbox>
   </object>
   <object>
      <name>table column header</name>
      <pose>Frontal</pose>
      <truncated>0</truncated>
      <difficult>0</difficult>
      <occluded>0</occluded>
      <bndbox>
         <xmin>36.4284</xmin>
         <ymin>36.9701</ymin>
         <xmax>318.6033</xmax>
         <ymax>62.3821</ymax>
      </bndbox>
   </object>
   <object>
      <name>table row</name>
      <pose>Frontal</pose>
      <truncated>0</truncated>
      <difficult>0</difficult>
      <occluded>0</occluded>
      <bndbox>
         <xmin>36.4284</xmin>
         <ymin>36.9701</ymin>
         <xmax>318.6033</xmax>
         <ymax>62.3820</ymax>
      </bndbox>
   </object>
   <object>
      <name>table row</name>
      <pose>Frontal</pose>
      <truncated>0</truncated>
      <difficult>0</difficult>
      <occluded>0</occluded>
      <bndbox>
         <xmin>36.4284</xmin>
         <ymin>62.3820</ymin>
         <xmax>318.6033</xmax>
         <ymax>89.5250</ymax>
      </bndbox>
   </object>
   <object>
      <name>table row</name>
      <pose>Frontal</pose>
      <truncated>0</truncated>
      <difficult>0</difficult>
      <occluded>0</occluded>
      <bndbox>
         <xmin>36.4284</xmin>
         <ymin>89.5250</ymin>
         <xmax>318.6033</xmax>
         <ymax>113.9397</ymax>
      </bndbox>
   </object>
   <object>
      <name>table column</name>
      <pose>Frontal</pose>
      <truncated>0</truncated>
      <difficult>0</difficult>
      <occluded>0</occluded>
      <bndbox>
         <xmin>36.4284</xmin>
         <ymin>36.9701</ymin>
         <xmax>140.4028</xmax>
         <ymax>113.9397</ymax>
      </bndbox>
   </object>
   <object>
      <name>table column</name>
      <pose>Frontal</pose>
      <truncated>0</truncated>
      <difficult>0</difficult>
      <occluded>0</occluded>
      <bndbox>
         <xmin>140.4028</xmin>
         <ymin>36.9701</ymin>
         <xmax>194.9289</xmax>
         <ymax>113.9397</ymax>
      </bndbox>
   </object>
   <object>
      <name>table column</name>
      <pose>Frontal</pose>
      <truncated>0</truncated>
      <difficult>0</difficult>
      <occluded>0</occluded>
      <bndbox>
         <xmin>194.9289</xmin>
         <ymin>36.9701</ymin>
         <xmax>253.3477</xmax>
         <ymax>113.9397</ymax>
      </bndbox>
   </object>
   <object>
      <name>table column</name>
      <pose>Frontal</pose>
      <truncated>0</truncated>
      <difficult>0</difficult>
      <occluded>0</occluded>
      <bndbox>
         <xmin>253.3477</xmin>
         <ymin>36.9701</ymin>
         <xmax>318.6033</xmax>
         <ymax>113.9397</ymax>
      </bndbox>
   </object>
</annotation>
